vk_teams_async_bot/__init__.py
vk_teams_async_bot/bot.py
vk_teams_async_bot/client_session.py
vk_teams_async_bot/constants.py
vk_teams_async_bot/dispatcher.py
vk_teams_async_bot/errors.py
vk_teams_async_bot/events.py
vk_teams_async_bot/filter.py
vk_teams_async_bot/handler.py
vk_teams_async_bot/helpers.py
vk_teams_async_bot/middleware.py
vk_teams_async_bot/schemas.py
vk_teams_async_bot/state.py
vk_teams_async_bot/timer.py
vk_teams_async_bot-0.2.7.dist-info/LICENSE
vk_teams_async_bot-0.2.7.dist-info/METADATA
vk_teams_async_bot-0.2.7.dist-info/WHEEL
vk_teams_async_bot-0.2.7.dist-info/RECORD
