Metadata-Version: 2.1
Name: vk-teams-async-bot
Version: 0.2.7
Summary: 
Home-page: https://github.com/Quakeer444/vk_teams_async_bot
License: MIT
Author: Александр Смирнов
Author-email: alexsmi4444@gmail.com
Requires-Python: >=3.11,<4.0
Classifier: License :: OSI Approved :: MIT License
Classifier: Programming Language :: Python :: 3
Classifier: Programming Language :: Python :: 3.11
Classifier: Programming Language :: Python :: 3.12
Requires-Dist: aiofiles (>=23.2.1,<24.0.0)
Requires-Dist: aiohttp (>=3.9.1,<4.0.0)
Requires-Dist: multidict (>=6.0.5,<7.0.0)
Requires-Dist: pydantic (>=2.5.2,<3.0.0)
Requires-Dist: pydantic-settings (>=2.1.0,<3.0.0)
Project-URL: Repository, https://github.com/Quakeer444/vk_teams_async_bot
